lynx/__init__.py
lynx/diagram.py
lynx/expression_eval.py
lynx/py.typed
lynx/render.py
lynx/schema.py
lynx/widget.py
lynx/blocks/__init__.py
lynx/blocks/base.py
lynx/blocks/gain.py
lynx/blocks/io_marker.py
lynx/blocks/state_space.py
lynx/blocks/sum.py
lynx/blocks/transfer_function.py
lynx/config/__init__.py
lynx/config/constants.py
lynx/conversion/__init__.py
lynx/conversion/block_converters.py
lynx/conversion/interconnect.py
lynx/conversion/signal_extraction.py
lynx/static/index.css
lynx/static/index.js
lynx/static/index.js.map
lynx/templates/README.md
lynx/templates/__init__.py
lynx/templates/_templates.py
lynx/templates/cascaded.json
lynx/templates/feedback_ss.json
lynx/templates/feedback_tf.json
lynx/templates/feedforward_ss.json
lynx/templates/feedforward_tf.json
lynx/templates/filtered_tf.json
lynx/templates/open_loop_ss.json
lynx/templates/open_loop_tf.json
lynx/utils/__init__.py
lynx/utils/error_handler.py
lynx/utils/ipython_utils.py
lynx/utils/latex_formatting.py
lynx/utils/logging_config.py
lynx/utils/plot_themes.py
lynx/utils/theme_config.py
lynx/validation/__init__.py
lynx/validation/algebraic_loop.py
lynx/validation/graph_validator.py
lynx/validation/input_validation.py
lynx_nb-0.1.4.dist-info/METADATA
lynx_nb-0.1.4.dist-info/WHEEL
lynx_nb-0.1.4.dist-info/RECORD
