Metadata-Version: 2.4
Name: lynx-nb
Version: 0.1.4
Summary: Block diagram editor for control systems
Author-email: Jared Callaham <jared.callaham@gmail.com>
Requires-Python: >=3.11
Requires-Dist: anywidget>=0.9.21
Requires-Dist: control>=0.10.1
Requires-Dist: numpy>=2.4.1
Requires-Dist: pydantic>=2.12.5
Requires-Dist: traitlets>=5.14.3
